hf_ocr/__init__.py
hf_ocr/ocr_pdf.py
hf_ocr_llamasearch-0.1.0rc625.dist-info/licenses/LICENSE
hf_ocr_llamasearch-0.1.0rc625.dist-info/METADATA
hf_ocr_llamasearch-0.1.0rc625.dist-info/WHEEL
hf_ocr_llamasearch-0.1.0rc625.dist-info/top_level.txt
hf_ocr_llamasearch-0.1.0rc625.dist-info/RECORD
